xn_twist/__init__.py
xn_twist/cli.py
xn_twist/xn_twist.py
xn_twist-1.4.0.dist-info/METADATA
xn_twist-1.4.0.dist-info/RECORD
xn_twist-1.4.0.dist-info/WHEEL
xn_twist-1.4.0.dist-info/entry_points.txt
xn_twist-1.4.0.dist-info/top_level.txt
