Metadata-Version: 2.1
Name: xn-twist
Version: 1.4.0
Summary: Unicode Domain-Squat Finder
Home-page: https://github.com/xn-twist/xn-twist
Author: Floyd Hightower
Author-email: UNKNOWN
License: MIT license
Keywords: xn_twist
Platform: UNKNOWN
Classifier: Development Status :: 2 - Pre-Alpha
Classifier: Intended Audience :: Developers
Classifier: License :: OSI Approved :: MIT License
Classifier: Natural Language :: English
Classifier: Programming Language :: Python :: 3
Classifier: Programming Language :: Python :: 3.3
Classifier: Programming Language :: Python :: 3.4
Classifier: Programming Language :: Python :: 3.5
Requires-Dist: dnspython
Requires-Dist: docopt (>=0.6)
Requires-Dist: tldextract
Requires-Dist: xn-twist-python-sdk
